mpl_events/__init__.py
mpl_events/__version__.py
mpl_events/_base.py
mpl_events/_logging.py
mpl_events/_types.py
mpl_events/filters.py
mpl_events/mpl.py
mpl_events-0.1.0.dist-info/LICENSE
mpl_events-0.1.0.dist-info/METADATA
mpl_events-0.1.0.dist-info/WHEEL
mpl_events-0.1.0.dist-info/top_level.txt
mpl_events-0.1.0.dist-info/RECORD
