Metadata-Version: 2.1
Name: mpl-events
Version: 0.1.0
Summary: A tiny library for simple and convenient matplotlib event handling
Home-page: https://github.com/espdev/mpl-events
Author: Eugene Prilepin
Author-email: esp.home@gmail.com
License: MIT
Platform: UNKNOWN
Classifier: Development Status :: 3 - Alpha
Classifier: Intended Audience :: Developers
Classifier: Intended Audience :: Science/Research
Classifier: Topic :: Scientific/Engineering :: Visualization
Classifier: License :: OSI Approved :: MIT License
Classifier: Programming Language :: Python
Classifier: Programming Language :: Python :: 3 :: Only
Classifier: Programming Language :: Python :: 3
Classifier: Programming Language :: Python :: 3.6
Classifier: Programming Language :: Python :: 3.7
Classifier: Programming Language :: Python :: Implementation :: CPython
Requires-Python: >=3.6, <4
Requires-Dist: matplotlib (<3.2,>=2.0)
